{"success": true, "data": 
[{"value":3698,"trip_class":0,"show_to_affiliates":false,"return_date":null,"origin":"SVX","number_of_changes":1,"gate":"Pobeda","found_at":"2020-03-18T17:21:00.467215","duration":855,"distance":2484,"destination":"KGD","depart_date":"2020-04-02","actual":true},{"value":3698,"trip_class":0,"show_to_affiliates":false,"return_date":null,"origin":"SVX","number_of_changes":1,"gate":"Pobeda","found_at":"2020-03-18T21:01:20.678782","duration":570,"distance":2484,"destination":"KGD","depart_date":"2020-03-31","actual":true},{"value":4098,"trip_class":0,"show_to_affiliates":false,"return_date":null,"origin":"SVX","number_of_changes":1,"gate":"Pobeda","found_at":"2020-03-18T21:04:25.163227","duration":855,"distance":2484,"destination":"KGD","depart_date":"2020-03-30","actual":true},{"value":4098,"trip_class":0,"show_to_affiliates":false,"return_date":null,"origin":"SVX","number_of_changes":1,"gate":"Pobeda","found_at":"2020-03-18T14:34:36.869306","duration":510,"distance":2484,"destination":"KGD","depart_date":"2020-04-01","actual":true},{"value":4198,"trip_class":0,"show_to_affiliates":false,"return_date":null,"origin":"SVX","number_of_changes":1,"gate":"KupiBilet.ru","found_at":"2020-03-18T01:32:19.606688","duration":855,"distance":2484,"destination":"KGD","depart_date":"2020-04-08","actual":true},{"value":4198,"trip_class":0,"show_to_affiliates":false,"return_date":null,"origin":"SVX","number_of_changes":1,"gate":"Pobeda","found_at":"2020-03-18T07:12:58.481463","duration":570,"distance":2484,"destination":"KGD","depart_date":"2020-04-07","actual":true},{"value":4198,"trip_class":0,"show_to_affiliates":false,"return_date":null,"origin":"SVX","number_of_changes":1,"gate":"Pobeda","found_at":"2020-03-18T17:19:53.633849","duration":855,"distance":2484,"destination":"KGD","depart_date":"2020-04-09","actual":true},{"value":4448,"trip_class":0,"show_to_affiliates":false,"return_date":null,"origin":"SVX","number_of_changes":1,"gate":"KupiBilet.ru","found_at":"2020-03-18T05:15:22.562624","duration":855,"distance":2484,"destination":"KGD","depart_date":"2020-04-13","actual":true},{"value":4448,"trip_class":0,"show_to_affiliates":false,"return_date":null,"origin":"SVX","number_of_changes":1,"gate":"KupiBilet.ru","found_at":"2020-03-18T17:21:45.023649","duration":855,"distance":2484,"destination":"KGD","depart_date":"2020-04-04","actual":true},{"value":4448,"trip_class":0,"show_to_affiliates":false,"return_date":null,"origin":"SVX","number_of_changes":1,"gate":"Pobeda","found_at":"2020-03-18T02:36:06.470720","duration":570,"distance":2484,"destination":"KGD","depart_date":"2020-04-12","actual":true},{"value":4448,"trip_class":0,"show_to_affiliates":false,"return_date":null,"origin":"SVX","number_of_changes":1,"gate":"Pobeda","found_at":"2020-03-18T14:36:26.507660","duration":370,"distance":2484,"destination":"KGD","depart_date":"2020-03-19","actual":true},{"value":4448,"trip_class":0,"show_to_affiliates":false,"return_date":null,"origin":"SVX","number_of_changes":1,"gate":"KupiBilet.ru","found_at":"2020-03-18T13:49:45.525303","duration":385,"distance":2484,"destination":"KGD","depart_date":"2020-03-21","actual":true},{"value":4565,"trip_class":0,"show_to_affiliates":false,"return_date":null,"origin":"SVX","number_of_changes":1,"gate":"Kiwi.com","found_at":"2020-03-18T19:29:45.367635","duration":790,"distance":2484,"destination":"KGD","depart_date":"2020-03-20","actual":true},{"value":4598,"trip_class":0,"show_to_affiliates":false,"return_date":null,"origin":"SVX","number_of_changes":1,"gate":"Pobeda","found_at":"2020-03-18T05:12:38.465482","duration":855,"distance":2484,"destination":"KGD","depart_date":"2020-04-06","actual":true},{"value":4598,"trip_class":0,"show_to_affiliates":false,"return_date":null,"origin":"SVX","number_of_changes":1,"gate":"Pobeda","found_at":"2020-03-17T23:32:13.688182","duration":855,"distance":2484,"destination":"KGD","depart_date":"2020-04-15","actual":true},{"value":4670,"trip_class":0,"show_to_affiliates":false,"return_date":null,"origin":"SVX","number_of_changes":1,"gate":"KupiBilet.ru","found_at":"2020-03-18T01:13:32.584312","duration":915,"distance":2484,"destination":"KGD","depart_date":"2020-04-05","actual":true},{"value":4698,"trip_class":0,"show_to_affiliates":false,"return_date":null,"origin":"SVX","number_of_changes":1,"gate":"Kiwi.com","found_at":"2020-03-18T21:00:11.505805","duration":1735,"distance":2484,"destination":"KGD","depart_date":"2020-03-28","actual":true},{"value":4747,"trip_class":0,"show_to_affiliates":false,"return_date":null,"origin":"SVX","number_of_changes":1,"gate":"Aviakassa","found_at":"2020-03-18T20:00:08.167085","duration":570,"distance":2484,"destination":"KGD","depart_date":"2020-04-03","actual":true},{"value":4848,"trip_class":0,"show_to_affiliates":false,"return_date":null,"origin":"SVX","number_of_changes":1,"gate":"KupiBilet.ru","found_at":"2020-03-18T04:47:39.376304","duration":570,"distance":2484,"destination":"KGD","depart_date":"2020-04-22","actual":true},{"value":4848,"trip_class":0,"show_to_affiliates":false,"return_date":null,"origin":"SVX","number_of_changes":1,"gate":"KupiBilet.ru","found_at":"2020-03-18T05:11:03.391440","duration":570,"distance":2484,"destination":"KGD","depart_date":"2020-04-19","actual":true},{"value":4848,"trip_class":0,"show_to_affiliates":false,"return_date":null,"origin":"SVX","number_of_changes":1,"gate":"KupiBilet.ru","found_at":"2020-03-18T10:57:14.335367","duration":855,"distance":2484,"destination":"KGD","depart_date":"2020-04-18","actual":true},{"value":4848,"trip_class":0,"show_to_affiliates":false,"return_date":null,"origin":"SVX","number_of_changes":1,"gate":"Pobeda","found_at":"2020-03-18T05:11:06.153150","duration":855,"distance":2484,"destination":"KGD","depart_date":"2020-04-11","actual":true},{"value":4848,"trip_class":0,"show_to_affiliates":false,"return_date":null,"origin":"SVX","number_of_changes":1,"gate":"Pobeda","found_at":"2020-03-18T02:37:30.674031","duration":510,"distance":2484,"destination":"KGD","depart_date":"2020-04-16","actual":true},{"value":4848,"trip_class":0,"show_to_affiliates":false,"return_date":null,"origin":"SVX","number_of_changes":1,"gate":"Pobeda","found_at":"2020-03-18T20:07:42.485873","duration":765,"distance":2484,"destination":"KGD","depart_date":"2020-03-24","actual":true},{"value":4848,"trip_class":0,"show_to_affiliates":false,"return_date":null,"origin":"SVX","number_of_changes":1,"gate":"KupiBilet.ru","found_at":"2020-03-18T04:46:57.416277","duration":570,"distance":2484,"destination":"KGD","depart_date":"2020-04-21","actual":true},{"value":4848,"trip_class":0,"show_to_affiliates":false,"return_date":null,"origin":"SVX","number_of_changes":1,"gate":"Pobeda","found_at":"2020-03-18T12:33:35.203003","duration":510,"distance":2484,"destination":"KGD","depart_date":"2020-04-23","actual":true},{"value":4848,"trip_class":0,"show_to_affiliates":false,"return_date":null,"origin":"SVX","number_of_changes":1,"gate":"KupiBilet.ru","found_at":"2020-03-18T11:23:43.271421","duration":855,"distance":2484,"destination":"KGD","depart_date":"2020-04-20","actual":true},{"value":4848,"trip_class":0,"show_to_affiliates":false,"return_date":null,"origin":"SVX","number_of_changes":1,"gate":"KupiBilet.ru","found_at":"2020-03-18T17:41:47.398684","duration":510,"distance":2484,"destination":"KGD","depart_date":"2020-04-10","actual":true},{"value":5090,"trip_class":0,"show_to_affiliates":false,"return_date":null,"origin":"SVX","number_of_changes":1,"gate":"KupiBilet.ru","found_at":"2020-03-18T20:13:52.930492","duration":960,"distance":2484,"destination":"KGD","depart_date":"2020-03-23","actual":true},{"value":5090,"trip_class":0,"show_to_affiliates":false,"return_date":null,"origin":"SVX","number_of_changes":1,"gate":"KupiBilet.ru","found_at":"2020-03-18T20:09:07.828955","duration":1025,"distance":2484,"destination":"KGD","depart_date":"2020-03-25","actual":true},{"value":5099,"trip_class":0,"show_to_affiliates":false,"return_date":null,"origin":"SVX","number_of_changes":1,"gate":"SuperKassa.ru","found_at":"2020-03-18T20:11:46.021248","duration":820,"distance":2484,"destination":"KGD","depart_date":"2020-03-27","actual":true},{"value":5143,"trip_class":0,"show_to_affiliates":false,"return_date":null,"origin":"SVX","number_of_changes":1,"gate":"Kiwi.com","found_at":"2020-03-18T05:46:25.981019","duration":790,"distance":2484,"destination":"KGD","depart_date":"2020-03-22","actual":true},{"value":5299,"trip_class":0,"show_to_affiliates":false,"return_date":null,"origin":"SVX","number_of_changes":1,"gate":"KupiBilet.ru","found_at":"2020-03-18T20:10:25.392990","duration":370,"distance":2484,"destination":"KGD","depart_date":"2020-03-26","actual":true},{"value":5299,"trip_class":0,"show_to_affiliates":false,"return_date":null,"origin":"SVX","number_of_changes":1,"gate":"Pobeda","found_at":"2020-03-18T01:17:32.389642","duration":855,"distance":2484,"destination":"KGD","depart_date":"2020-04-17","actual":true},{"value":5699,"trip_class":0,"show_to_affiliates":false,"return_date":null,"origin":"SVX","number_of_changes":1,"gate":"Pobeda","found_at":"2020-03-18T03:47:52.222069","duration":585,"distance":2484,"destination":"KGD","depart_date":"2020-05-21","actual":true},{"value":5699,"trip_class":0,"show_to_affiliates":false,"return_date":null,"origin":"SVX","number_of_changes":1,"gate":"KupiBilet.ru","found_at":"2020-03-18T03:35:55.764949","duration":585,"distance":2484,"destination":"KGD","depart_date":"2020-05-20","actual":true},{"value":5699,"trip_class":0,"show_to_affiliates":false,"return_date":null,"origin":"SVX","number_of_changes":1,"gate":"Pobeda","found_at":"2020-03-17T23:27:36.121919","duration":855,"distance":2484,"destination":"KGD","depart_date":"2020-05-05","actual":true},{"value":5699,"trip_class":0,"show_to_affiliates":false,"return_date":null,"origin":"SVX","number_of_changes":1,"gate":"KupiBilet.ru","found_at":"2020-03-18T03:43:31.942278","duration":585,"distance":2484,"destination":"KGD","depart_date":"2020-05-18","actual":true},{"value":5699,"trip_class":0,"show_to_affiliates":false,"return_date":null,"origin":"SVX","number_of_changes":1,"gate":"Pobeda","found_at":"2020-03-18T04:02:18.827807","duration":855,"distance":2484,"destination":"KGD","depart_date":"2020-04-26","actual":true},{"value":5699,"trip_class":0,"show_to_affiliates":false,"return_date":null,"origin":"SVX","number_of_changes":1,"gate":"Pobeda","found_at":"2020-03-18T11:01:48.544948","duration":855,"distance":2484,"destination":"KGD","depart_date":"2020-05-15","actual":true},{"value":5699,"trip_class":0,"show_to_affiliates":false,"return_date":null,"origin":"SVX","number_of_changes":1,"gate":"Pobeda","found_at":"2020-03-18T12:34:46.111045","duration":645,"distance":2484,"destination":"KGD","depart_date":"2020-05-07","actual":true},{"value":5747,"trip_class":0,"show_to_affiliates":false,"return_date":null,"origin":"SVX","number_of_changes":1,"gate":"Kiwi.com","found_at":"2020-03-17T22:41:37.850555","duration":1425,"distance":2484,"destination":"KGD","depart_date":"2020-05-28","actual":true},{"value":5794,"trip_class":0,"show_to_affiliates":false,"return_date":null,"origin":"SVX","number_of_changes":1,"gate":"Aviakassa","found_at":"2020-03-18T04:43:56.679737","duration":1565,"distance":2484,"destination":"KGD","depart_date":"2020-03-18","actual":true},{"value":5899,"trip_class":0,"show_to_affiliates":false,"return_date":null,"origin":"SVX","number_of_changes":1,"gate":"KupiBilet.ru","found_at":"2020-03-17T22:19:45.099641","duration":645,"distance":2484,"destination":"KGD","depart_date":"2020-05-27","actual":true},{"value":5963,"trip_class":0,"show_to_affiliates":false,"return_date":null,"origin":"SVX","number_of_changes":1,"gate":"Biletix","found_at":"2020-03-18T05:32:07.356212","duration":585,"distance":2484,"destination":"KGD","depart_date":"2020-05-11","actual":true},{"value":6047,"trip_class":0,"show_to_affiliates":false,"return_date":null,"origin":"SVX","number_of_changes":1,"gate":"Aviakassa","found_at":"2020-03-18T05:33:09.108526","duration":915,"distance":2484,"destination":"KGD","depart_date":"2020-04-27","actual":true},{"value":6099,"trip_class":0,"show_to_affiliates":false,"return_date":null,"origin":"SVX","number_of_changes":1,"gate":"Pobeda","found_at":"2020-03-18T12:33:14.167795","duration":855,"distance":2484,"destination":"KGD","depart_date":"2020-04-24","actual":true},{"value":6099,"trip_class":0,"show_to_affiliates":false,"return_date":null,"origin":"SVX","number_of_changes":1,"gate":"KupiBilet.ru","found_at":"2020-03-18T01:18:30.999091","duration":855,"distance":2484,"destination":"KGD","depart_date":"2020-05-04","actual":true},{"value":6099,"trip_class":0,"show_to_affiliates":false,"return_date":null,"origin":"SVX","number_of_changes":1,"gate":"KupiBilet.ru","found_at":"2020-03-18T19:39:24.932309","duration":645,"distance":2484,"destination":"KGD","depart_date":"2020-10-16","actual":true},{"value":6100,"trip_class":0,"show_to_affiliates":false,"return_date":null,"origin":"SVX","number_of_changes":1,"gate":"Kiwi.com","found_at":"2020-03-17T22:09:36.248832","duration":1725,"distance":2484,"destination":"KGD","depart_date":"2020-05-30","actual":true},{"value":6117,"trip_class":0,"show_to_affiliates":false,"return_date":null,"origin":"SVX","number_of_changes":1,"gate":"SuperKassa.ru","found_at":"2020-03-18T20:29:17.755339","duration":765,"distance":2484,"destination":"KGD","depart_date":"2020-05-29","actual":true},{"value":6132,"trip_class":0,"show_to_affiliates":false,"return_date":null,"origin":"SVX","number_of_changes":1,"gate":"SuperKassa.ru","found_at":"2020-03-18T03:28:59.396553","duration":670,"distance":2484,"destination":"KGD","depart_date":"2020-05-10","actual":true},{"value":6299,"trip_class":0,"show_to_affiliates":false,"return_date":null,"origin":"SVX","number_of_changes":1,"gate":"KupiBilet.ru","found_at":"2020-03-17T22:46:48.107212","duration":645,"distance":2484,"destination":"KGD","depart_date":"2020-05-12","actual":true},{"value":6299,"trip_class":0,"show_to_affiliates":false,"return_date":null,"origin":"SVX","number_of_changes":1,"gate":"Pobeda","found_at":"2020-03-18T04:18:42.859987","duration":585,"distance":2484,"destination":"KGD","depart_date":"2020-05-22","actual":true},{"value":6299,"trip_class":0,"show_to_affiliates":false,"return_date":null,"origin":"SVX","number_of_changes":1,"gate":"Pobeda","found_at":"2020-03-18T20:48:50.623279","duration":585,"distance":2484,"destination":"KGD","depart_date":"2020-05-25","actual":true},{"value":6438,"trip_class":0,"show_to_affiliates":false,"return_date":null,"origin":"SVX","number_of_changes":1,"gate":"Aviakassa","found_at":"2020-03-17T22:38:37.017135","duration":1635,"distance":2484,"destination":"KGD","depart_date":"2020-05-09","actual":true},{"value":6579,"trip_class":0,"show_to_affiliates":false,"return_date":null,"origin":"SVX","number_of_changes":1,"gate":"Aviakassa","found_at":"2020-03-18T06:55:19.665471","duration":785,"distance":2484,"destination":"KGD","depart_date":"2020-04-25","actual":true},{"value":6579,"trip_class":0,"show_to_affiliates":false,"return_date":null,"origin":"SVX","number_of_changes":1,"gate":"Aviakassa","found_at":"2020-03-18T05:31:10.767797","duration":725,"distance":2484,"destination":"KGD","depart_date":"2020-04-28","actual":true},{"value":6699,"trip_class":0,"show_to_affiliates":false,"return_date":null,"origin":"SVX","number_of_changes":1,"gate":"KupiBilet.ru","found_at":"2020-03-18T11:45:29.720496","duration":585,"distance":2484,"destination":"KGD","depart_date":"2020-06-08","actual":true},{"value":6699,"trip_class":0,"show_to_affiliates":false,"return_date":null,"origin":"SVX","number_of_changes":1,"gate":"KupiBilet.ru","found_at":"2020-03-18T03:45:27.660921","duration":645,"distance":2484,"destination":"KGD","depart_date":"2020-06-09","actual":true},{"value":6699,"trip_class":0,"show_to_affiliates":false,"return_date":null,"origin":"SVX","number_of_changes":1,"gate":"KupiBilet.ru","found_at":"2020-03-18T11:45:01.717366","duration":645,"distance":2484,"destination":"KGD","depart_date":"2020-06-10","actual":true},{"value":6716,"trip_class":0,"show_to_affiliates":false,"return_date":null,"origin":"SVX","number_of_changes":1,"gate":"KupiBilet.ru","found_at":"2020-03-18T03:05:43.560265","duration":670,"distance":2484,"destination":"KGD","depart_date":"2020-05-03","actual":true},{"value":6787,"trip_class":0,"show_to_affiliates":false,"return_date":null,"origin":"SVX","number_of_changes":1,"gate":"Kiwi.com","found_at":"2020-03-17T22:45:33.100426","duration":930,"distance":2484,"destination":"KGD","depart_date":"2020-05-08","actual":true},{"value":7091,"trip_class":0,"show_to_affiliates":false,"return_date":null,"origin":"SVX","number_of_changes":1,"gate":"SuperKassa.ru","found_at":"2020-03-18T04:45:39.893611","duration":885,"distance":2484,"destination":"KGD","depart_date":"2020-09-01","actual":true},{"value":7091,"trip_class":0,"show_to_affiliates":false,"return_date":null,"origin":"SVX","number_of_changes":1,"gate":"SuperKassa.ru","found_at":"2020-03-18T03:24:44.584476","duration":885,"distance":2484,"destination":"KGD","depart_date":"2020-09-19","actual":true},{"value":7150,"trip_class":0,"show_to_affiliates":false,"return_date":null,"origin":"SVX","number_of_changes":1,"gate":"SuperKassa.ru","found_at":"2020-03-18T11:43:28.470696","duration":750,"distance":2484,"destination":"KGD","depart_date":"2020-06-26","actual":true},{"value":7251,"trip_class":0,"show_to_affiliates":false,"return_date":null,"origin":"SVX","number_of_changes":1,"gate":"KupiBilet.ru","found_at":"2020-03-17T23:25:13.518284","duration":550,"distance":2484,"destination":"KGD","depart_date":"2020-06-14","actual":true},{"value":7435,"trip_class":0,"show_to_affiliates":false,"return_date":null,"origin":"SVX","number_of_changes":1,"gate":"Aviakassa","found_at":"2020-03-18T00:21:20.650307","duration":885,"distance":2484,"destination":"KGD","depart_date":"2020-09-05","actual":true},{"value":7545,"trip_class":0,"show_to_affiliates":false,"return_date":null,"origin":"SVX","number_of_changes":1,"gate":"Aviakassa","found_at":"2020-03-17T22:44:40.263664","duration":750,"distance":2484,"destination":"KGD","depart_date":"2020-06-19","actual":true},{"value":7554,"trip_class":0,"show_to_affiliates":false,"return_date":null,"origin":"SVX","number_of_changes":1,"gate":"SuperKassa.ru","found_at":"2020-03-18T12:46:29.829966","duration":815,"distance":2484,"destination":"KGD","depart_date":"2020-07-31","actual":true},{"value":7569,"trip_class":0,"show_to_affiliates":false,"return_date":null,"origin":"SVX","number_of_changes":1,"gate":"SuperKassa.ru","found_at":"2020-03-18T15:38:28.561849","duration":885,"distance":2484,"destination":"KGD","depart_date":"2020-06-22","actual":true},{"value":7569,"trip_class":0,"show_to_affiliates":false,"return_date":null,"origin":"SVX","number_of_changes":1,"gate":"SuperKassa.ru","found_at":"2020-03-18T03:28:18.296250","duration":885,"distance":2484,"destination":"KGD","depart_date":"2020-06-12","actual":true},{"value":7569,"trip_class":0,"show_to_affiliates":false,"return_date":null,"origin":"SVX","number_of_changes":1,"gate":"SuperKassa.ru","found_at":"2020-03-17T23:15:14.706714","duration":885,"distance":2484,"destination":"KGD","depart_date":"2020-06-15","actual":true},{"value":7569,"trip_class":0,"show_to_affiliates":false,"return_date":null,"origin":"SVX","number_of_changes":1,"gate":"SuperKassa.ru","found_at":"2020-03-17T18:48:01.104383","duration":885,"distance":2484,"destination":"KGD","depart_date":"2020-06-05","actual":true},{"value":7569,"trip_class":0,"show_to_affiliates":false,"return_date":null,"origin":"SVX","number_of_changes":1,"gate":"SuperKassa.ru","found_at":"2020-03-17T23:54:08.957137","duration":885,"distance":2484,"destination":"KGD","depart_date":"2020-06-17","actual":true},{"value":7569,"trip_class":0,"show_to_affiliates":false,"return_date":null,"origin":"SVX","number_of_changes":1,"gate":"SuperKassa.ru","found_at":"2020-03-18T02:55:07.570329","duration":885,"distance":2484,"destination":"KGD","depart_date":"2020-06-30","actual":true},{"value":7980,"trip_class":0,"show_to_affiliates":false,"return_date":null,"origin":"SVX","number_of_changes":1,"gate":"SuperKassa.ru","found_at":"2020-03-18T04:44:57.388506","duration":405,"distance":2484,"destination":"KGD","depart_date":"2020-06-11","actual":true},{"value":7984,"trip_class":0,"show_to_affiliates":false,"return_date":null,"origin":"SVX","number_of_changes":1,"gate":"SuperKassa.ru","found_at":"2020-03-18T17:03:44.905430","duration":885,"distance":2484,"destination":"KGD","depart_date":"2020-08-11","actual":true},{"value":7984,"trip_class":0,"show_to_affiliates":false,"return_date":null,"origin":"SVX","number_of_changes":1,"gate":"SuperKassa.ru","found_at":"2020-03-17T19:36:52.795981","duration":885,"distance":2484,"destination":"KGD","depart_date":"2020-08-17","actual":true},{"value":7984,"trip_class":0,"show_to_affiliates":false,"return_date":null,"origin":"SVX","number_of_changes":1,"gate":"SuperKassa.ru","found_at":"2020-03-18T10:29:05.442974","duration":885,"distance":2484,"destination":"KGD","depart_date":"2020-07-30","actual":true},{"value":7984,"trip_class":0,"show_to_affiliates":false,"return_date":null,"origin":"SVX","number_of_changes":1,"gate":"SuperKassa.ru","found_at":"2020-03-17T18:03:09.936393","duration":885,"distance":2484,"destination":"KGD","depart_date":"2020-07-06","actual":true},{"value":7984,"trip_class":0,"show_to_affiliates":false,"return_date":null,"origin":"SVX","number_of_changes":1,"gate":"SuperKassa.ru","found_at":"2020-03-18T00:35:58.745669","duration":885,"distance":2484,"destination":"KGD","depart_date":"2020-07-15","actual":true},{"value":7984,"trip_class":0,"show_to_affiliates":false,"return_date":null,"origin":"SVX","number_of_changes":1,"gate":"SuperKassa.ru","found_at":"2020-03-18T10:19:20.288629","duration":885,"distance":2484,"destination":"KGD","depart_date":"2020-07-29","actual":true},{"value":7984,"trip_class":0,"show_to_affiliates":false,"return_date":null,"origin":"SVX","number_of_changes":1,"gate":"SuperKassa.ru","found_at":"2020-03-17T23:13:57.916172","duration":885,"distance":2484,"destination":"KGD","depart_date":"2020-07-12","actual":true},{"value":7984,"trip_class":0,"show_to_affiliates":false,"return_date":null,"origin":"SVX","number_of_changes":1,"gate":"SuperKassa.ru","found_at":"2020-03-18T11:11:27.295918","duration":885,"distance":2484,"destination":"KGD","depart_date":"2020-07-01","actual":true},{"value":7984,"trip_class":0,"show_to_affiliates":false,"return_date":null,"origin":"SVX","number_of_changes":1,"gate":"SuperKassa.ru","found_at":"2020-03-17T23:51:40.693332","duration":885,"distance":2484,"destination":"KGD","depart_date":"2020-08-06","actual":true},{"value":7984,"trip_class":0,"show_to_affiliates":false,"return_date":null,"origin":"SVX","number_of_changes":1,"gate":"SuperKassa.ru","found_at":"2020-03-14T08:09:54.460020","duration":885,"distance":2484,"destination":"KGD","depart_date":"2020-07-26","actual":true},{"value":7984,"trip_class":0,"show_to_affiliates":false,"return_date":null,"origin":"SVX","number_of_changes":1,"gate":"SuperKassa.ru","found_at":"2020-03-18T00:11:39.939134","duration":885,"distance":2484,"destination":"KGD","depart_date":"2020-08-05","actual":true},{"value":7984,"trip_class":0,"show_to_affiliates":false,"return_date":null,"origin":"SVX","number_of_changes":1,"gate":"SuperKassa.ru","found_at":"2020-03-18T15:18:44.354568","duration":885,"distance":2484,"destination":"KGD","depart_date":"2020-07-20","actual":true},{"value":7984,"trip_class":0,"show_to_affiliates":false,"return_date":null,"origin":"SVX","number_of_changes":1,"gate":"SuperKassa.ru","found_at":"2020-03-17T23:23:03.890510","duration":885,"distance":2484,"destination":"KGD","depart_date":"2020-07-14","actual":true},{"value":7984,"trip_class":0,"show_to_affiliates":false,"return_date":null,"origin":"SVX","number_of_changes":1,"gate":"SuperKassa.ru","found_at":"2020-03-18T01:55:55.122263","duration":885,"distance":2484,"destination":"KGD","depart_date":"2020-07-02","actual":true},{"value":7984,"trip_class":0,"show_to_affiliates":false,"return_date":null,"origin":"SVX","number_of_changes":1,"gate":"SuperKassa.ru","found_at":"2020-03-17T23:18:00.090520","duration":885,"distance":2484,"destination":"KGD","depart_date":"2020-07-05","actual":true},{"value":7984,"trip_class":0,"show_to_affiliates":false,"return_date":null,"origin":"SVX","number_of_changes":1,"gate":"SuperKassa.ru","found_at":"2020-03-18T20:01:13.844744","duration":885,"distance":2484,"destination":"KGD","depart_date":"2020-07-17","actual":true},{"value":7984,"trip_class":0,"show_to_affiliates":false,"return_date":null,"origin":"SVX","number_of_changes":1,"gate":"SuperKassa.ru","found_at":"2020-03-17T23:29:27.105079","duration":885,"distance":2484,"destination":"KGD","depart_date":"2020-07-13","actual":true},{"value":7984,"trip_class":0,"show_to_affiliates":false,"return_date":null,"origin":"SVX","number_of_changes":1,"gate":"SuperKassa.ru","found_at":"2020-03-18T17:05:16.593066","duration":885,"distance":2484,"destination":"KGD","depart_date":"2020-08-08","actual":true},{"value":8048,"trip_class":0,"show_to_affiliates":false,"return_date":null,"origin":"SVX","number_of_changes":1,"gate":"Aviakassa","found_at":"2020-03-17T23:05:47.935650","duration":1250,"distance":2484,"destination":"KGD","depart_date":"2020-05-02","actual":true},{"value":8200,"trip_class":0,"show_to_affiliates":false,"return_date":null,"origin":"SVX","number_of_changes":1,"gate":"KupiBilet.ru","found_at":"2020-03-18T20:11:41.326859","duration":645,"distance":2484,"destination":"KGD","depart_date":"2020-08-30","actual":true},{"value":8258,"trip_class":0,"show_to_affiliates":false,"return_date":null,"origin":"SVX","number_of_changes":1,"gate":"Aviakassa","found_at":"2020-03-18T04:08:26.353441","duration":560,"distance":2484,"destination":"KGD","depart_date":"2021-01-25","actual":true},{"value":8296,"trip_class":0,"show_to_affiliates":false,"return_date":null,"origin":"SVX","number_of_changes":1,"gate":"Kiwi.com","found_at":"2020-03-17T19:13:10.757467","duration":630,"distance":2484,"destination":"KGD","depart_date":"2020-07-21","actual":true},{"value":8307,"trip_class":0,"show_to_affiliates":false,"return_date":null,"origin":"SVX","number_of_changes":1,"gate":"MEGO.travel","found_at":"2020-03-18T01:47:21.460431","duration":1290,"distance":2484,"destination":"KGD","depart_date":"2021-03-09","actual":true},{"value":8313,"trip_class":0,"show_to_affiliates":false,"return_date":null,"origin":"SVX","number_of_changes":1,"gate":"Kiwi.com","found_at":"2020-03-17T18:31:53.464749","duration":355,"distance":2484,"destination":"KGD","depart_date":"2021-01-01","actual":true},{"value":8350,"trip_class":0,"show_to_affiliates":false,"return_date":null,"origin":"SVX","number_of_changes":1,"gate":"SuperKassa.ru","found_at":"2020-03-18T20:03:02.621172","duration":690,"distance":2484,"destination":"KGD","depart_date":"2020-07-24","actual":true},{"value":8350,"trip_class":0,"show_to_affiliates":false,"return_date":null,"origin":"SVX","number_of_changes":1,"gate":"SuperKassa.ru","found_at":"2020-03-18T14:36:18.775026","duration":690,"distance":2484,"destination":"KGD","depart_date":"2020-07-04","actual":true},{"value":8363,"trip_class":0,"show_to_affiliates":false,"return_date":null,"origin":"SVX","number_of_changes":1,"gate":"Kiwi.com","found_at":"2020-03-17T22:43:12.785936","duration":1520,"distance":2484,"destination":"KGD","depart_date":"2020-07-08","actual":true},{"value":8446,"trip_class":0,"show_to_affiliates":false,"return_date":null,"origin":"SVX","number_of_changes":1,"gate":"Aviakassa","found_at":"2020-03-18T17:01:09.577109","duration":1410,"distance":2484,"destination":"KGD","depart_date":"2020-08-10","actual":true},{"value":8446,"trip_class":0,"show_to_affiliates":false,"return_date":null,"origin":"SVX","number_of_changes":1,"gate":"Aviakassa","found_at":"2020-03-17T17:58:55.322119","duration":1170,"distance":2484,"destination":"KGD","depart_date":"2020-11-01","actual":true},{"value":8446,"trip_class":0,"show_to_affiliates":false,"return_date":null,"origin":"SVX","number_of_changes":1,"gate":"KupiBilet.ru","found_at":"2020-03-17T22:51:38.937196","duration":1680,"distance":2484,"destination":"KGD","depart_date":"2020-08-01","actual":true},{"value":8446,"trip_class":0,"show_to_affiliates":false,"return_date":null,"origin":"SVX","number_of_changes":1,"gate":"KupiBilet.ru","found_at":"2020-03-18T14:38:00.024269","duration":1520,"distance":2484,"destination":"KGD","depart_date":"2020-07-03","actual":true},{"value":8503,"trip_class":0,"show_to_affiliates":false,"return_date":null,"origin":"SVX","number_of_changes":1,"gate":"SuperKassa.ru","found_at":"2020-03-18T01:02:13.591717","duration":885,"distance":2484,"destination":"KGD","depart_date":"2020-07-10","actual":true},{"value":8699,"trip_class":0,"show_to_affiliates":false,"return_date":null,"origin":"SVX","number_of_changes":1,"gate":"Pobeda","found_at":"2020-03-18T03:07:13.456087","duration":855,"distance":2484,"destination":"KGD","depart_date":"2020-04-29","actual":true},{"value":8802,"trip_class":0,"show_to_affiliates":false,"return_date":null,"origin":"SVX","number_of_changes":1,"gate":"S7 Airlines","found_at":"2020-03-18T18:23:33.584318","duration":1650,"distance":2484,"destination":"KGD","depart_date":"2021-03-02","actual":true},{"value":9820,"trip_class":0,"show_to_affiliates":false,"return_date":null,"origin":"SVX","number_of_changes":1,"gate":"KupiBilet.ru","found_at":"2020-03-18T05:51:10.776952","duration":1080,"distance":2484,"destination":"KGD","depart_date":"2020-05-01","actual":true},{"value":10167,"trip_class":0,"show_to_affiliates":false,"return_date":null,"origin":"SVX","number_of_changes":1,"gate":"Aviakassa","found_at":"2020-03-17T22:10:18.454544","duration":1390,"distance":2484,"destination":"KGD","depart_date":"2020-04-30","actual":true}] }
